dq_tester/__init__.py
dq_tester/cli.py
dq_tester/dashboard.py
dq_tester/factory.py
dq_tester/loaders.py
dq_tester/utils.py
dq_tester/validators.py
dq_tester/models/__init__.py
dq_tester/models/catalog.py
dq_tester/models/connections.py
dq_tester/models/test_plan.py
dq_tester/testers/__init__.py
dq_tester/testers/base.py
dq_tester/testers/csv.py
dq_tester/testers/database.py
dq_tester-0.4.0.dist-info/licenses/LICENSE
dq_tester-0.4.0.dist-info/METADATA
dq_tester-0.4.0.dist-info/WHEEL
dq_tester-0.4.0.dist-info/entry_points.txt
dq_tester-0.4.0.dist-info/top_level.txt
dq_tester-0.4.0.dist-info/RECORD
