Metadata-Version: 2.4
Name: dq_tester
Version: 0.4.0
Summary: A lightweight data quality testing tool for CSV files and databases
Author-email: Chad Ongstad <chad@kodda.io>
License: MIT
Project-URL: Homepage, https://github.com/koddachad/dq_tester
Project-URL: Repository, https://github.com/koddachad/dq_tester
Project-URL: Issues, https://github.com/koddachad/dq_tester/issues
Keywords: data quality,testing,csv,database,duckdb
Classifier: Development Status :: 4 - Beta
Classifier: Intended Audience :: Developers
Classifier: License :: OSI Approved :: MIT License
Classifier: Programming Language :: Python :: 3
Classifier: Programming Language :: Python :: 3.9
Classifier: Programming Language :: Python :: 3.10
Classifier: Programming Language :: Python :: 3.11
Classifier: Programming Language :: Python :: 3.12
Classifier: Programming Language :: Python :: 3.13
Classifier: Topic :: Software Development :: Quality Assurance
Classifier: Topic :: Software Development :: Testing
Requires-Python: >=3.9
License-File: LICENSE
Requires-Dist: pyyaml==6.0.3
Requires-Dist: duckdb==1.4.0
Requires-Dist: pydantic==2.11.9
Requires-Dist: tabulate==0.9.0
Requires-Dist: pyodbc==5.2.0
Requires-Dist: streamlit>=1.28.0
Requires-Dist: pandas>=2.0.0
Requires-Dist: plotly>=5.17.0
Dynamic: license-file
